rrrelay.py
rrrelay-1.0.2.dist-info/LICENSE
rrrelay-1.0.2.dist-info/METADATA
rrrelay-1.0.2.dist-info/WHEEL
rrrelay-1.0.2.dist-info/entry_points.txt
rrrelay-1.0.2.dist-info/top_level.txt
rrrelay-1.0.2.dist-info/RECORD
