Metadata-Version: 2.1
Name: rrrelay
Version: 1.0.2
Summary: Race Result and TB Relay
Author-email: Nathan Fraser <ndf-zz@6-v.org>
License: MIT
Project-URL: homepage, https://github.com/ndf-zz/rrrelay
Keywords: timing,tracking
Classifier: Development Status :: 3 - Alpha
Classifier: Topic :: Other/Nonlisted Topic
Classifier: Operating System :: OS Independent
Classifier: Programming Language :: Python :: 3
Requires-Python: >=3.6
License-File: LICENSE
Requires-Dist: tornado
Requires-Dist: metarace
